{
  "type": "FeatureCollection",
  "features": [
    {
      "type": "Feature",
      "id": 797937,
      "geometry": {
        "type": "Point",
        "coordinates": [
          146.75520000031423,
          -19.218249999928464
        ]
      },
      "properties": {
        "objectid": 797937,
        "globalid": "{9555EF3C-2D12-44D1-8839-32552425660E}",
        "what_was_observed": "Crocodile",
        "sighting": "I did",
        "sighttime": 1735286100000,
        "species": "Estuarine",
        "sightingid": "271224TSV1",
        "publicstatus": "Under Investigation",
        "publicinfo": "",
        "managementunit": "Townsville Operations",
        "lga": "Townsville City",
        "created_date": 1735286341000,
        "last_edited_date": 1735290775000,
        "closeddate": null
      }
    },
    {
      "type": "Feature",
      "id": 798737,
      "geometry": {
        "type": "Point",
        "coordinates": [
          145.98361111154082,
          -16.932777777391383
        ]
      },
      "properties": {
        "objectid": 798737,
        "globalid": "{1D6D5B32-DD30-4265-ADE1-DFC8BBF20C59}",
        "what_was_observed": "Crocodile",
        "sighting": "I did",
        "sighttime": 1735281000000,
        "species": "Estuarine",
        "sightingid": "271224CNS3",
        "publicstatus": "Under Investigation",
        "publicinfo": "",
        "managementunit": "Cairns Operations",
        "lga": "Cairns Regional",
        "created_date": 1735292119000,
        "last_edited_date": 1735292538000,
        "closeddate": null
      }
    },
    {
      "type": "Feature",
      "id": 798337,
      "geometry": {
        "type": "Point",
        "coordinates": [
          148.7225935999374,
          -20.650209177987694
        ]
      },
      "properties": {
        "objectid": 798337,
        "globalid": "{D1951021-0508-4F30-B524-9E52DA3F6AC7}",
        "what_was_observed": "Crocodile",
        "sighting": "I did",
        "sighttime": 1735273800000,
        "species": "Estuarine",
        "sightingid": "271224MKY1",
        "publicstatus": "Under Investigation",
        "publicinfo": "",
        "managementunit": "Mackay Operations",
        "lga": "Mackay Regional",
        "created_date": 1735291524000,
        "last_edited_date": 1735292558000,
        "closeddate": null
      }
    },
    {
      "type": "Feature",
      "id": 797537,
      "geometry": {
        "type": "Point",
        "coordinates": [
          145.7027777778881,
          -16.91305555512859
        ]
      },
      "properties": {
        "objectid": 797537,
        "globalid": "{242E517D-C108-40F3-8ABA-08913D8D1A80}",
        "what_was_observed": "Crocodile",
        "sighting": "I did",
        "sighttime": 1735252200000,
        "species": "Estuarine",
        "sightingid": "271224CNS2",
        "publicstatus": "Under Investigation",
        "publicinfo": "",
        "managementunit": "Cairns Operations",
        "lga": "Cairns Regional",
        "created_date": 1735257282000,
        "last_edited_date": 1735257844000,
        "closeddate": null
      }
    },
    {
      "type": "Feature",
      "id": 796737,
      "geometry": {
        "type": "Point",
        "coordinates": [
          146.0249810465557,
          -17.352572978847682
        ]
      },
      "properties": {
        "objectid": 796737,
        "globalid": "{D0CF686A-50E3-4C2E-A196-E70CD900570B}",
        "what_was_observed": "Crocodile",
        "sighting": "Somebody else",
        "sighttime": 1735245000000,
        "species": "Estuarine",
        "sightingid": "271224CNS1",
        "publicstatus": "Under Investigation",
        "publicinfo": "",
        "managementunit": "Cairns Operations",
        "lga": "Cairns Regional",
        "created_date": 1735248273000,
        "last_edited_date": 1735250733000,
        "closeddate": null
      }
    }
  ]
}
