{
  "type": "FeatureCollection",
  "features": [
    {
      "type": "Feature",
      "id": 807537,
      "geometry": {
        "type": "Point",
        "coordinates": [
          145.7035460000511,
          -16.884481999780533
        ]
      },
      "properties": {
        "objectid": 807537,
        "globalid": "{4B2A18BE-815D-45D2-B1DE-4DF53E94C1DD}",
        "what_was_observed": "Crocodile",
        "sighting": "I did",
        "sighttime": 1735717500000,
        "species": "Estuarine",
        "sightingid": "010125CNS1",
        "publicstatus": "Under Investigation",
        "publicinfo": "",
        "managementunit": "Cairns Operations",
        "lga": "Cairns Regional",
        "created_date": 1735718089000,
        "last_edited_date": 1735720900000,
        "closeddate": null
      }
    },
    {
      "type": "Feature",
      "id": 807937,
      "geometry": {
        "type": "Point",
        "coordinates": [
          146.73646591443995,
          -19.316287628940216
        ]
      },
      "properties": {
        "objectid": 807937,
        "globalid": "{54203BB2-3D83-4239-A389-B3E6A80188F9}",
        "what_was_observed": "Crocodile",
        "sighting": "I did",
        "sighttime": 1735716900000,
        "species": "Freshwater",
        "sightingid": "010125TSV1",
        "publicstatus": "Under Investigation",
        "publicinfo": "",
        "managementunit": "Townsville Operations",
        "lga": "Townsville City",
        "created_date": 1735729209000,
        "last_edited_date": 1735729623000,
        "closeddate": null
      }
    }
  ]
}
