{
  "type": "FeatureCollection",
  "features": [
    {
      "type": "Feature",
      "id": 1037144,
      "geometry": {
        "type": "Point",
        "coordinates": [
          141.62144671481562,
          -14.918242283155442
        ]
      },
      "properties": {
        "objectid": 1037144,
        "globalid": "{87246B53-9D85-4FFD-8A7F-61B07E9C4082}",
        "what_was_observed": "Crocodile",
        "sighting": "I did",
        "sighttime": 1749613140000,
        "species": "Estuarine",
        "sightingid": "110625PPA1",
        "publicstatus": "Under Investigation",
        "publicinfo": "",
        "managementunit": "Remote Operations",
        "lga": "Pormpuraaw Aboriginal Shire",
        "created_date": 1749613437000,
        "last_edited_date": 1749616663000,
        "closeddate": null
      }
    },
    {
      "type": "Feature",
      "id": 1037143,
      "geometry": {
        "type": "Point",
        "coordinates": [
          145.48145342736842,
          -16.552979821968481
        ]
      },
      "properties": {
        "objectid": 1037143,
        "globalid": "{5C34FC0E-467A-4A45-86A9-D3BED8697E9D}",
        "what_was_observed": "Crocodile",
        "sighting": "I did",
        "sighttime": 1749610980000,
        "species": "Estuarine",
        "sightingid": "110625DUG1",
        "publicstatus": "No Further Action",
        "publicinfo": "",
        "managementunit": "Cairns Operations",
        "lga": "Douglas Shire",
        "created_date": 1749611214000,
        "last_edited_date": 1749620160000,
        "closeddate": 1749620155000
      }
    }
  ]
}
