{
  "type": "FeatureCollection",
  "features": [
    {
      "type": "Feature",
      "id": 636735,
      "geometry": {
        "type": "Point",
        "coordinates": [
          146.7332499996217,
          -19.321099999833063
        ]
      },
      "properties": {
        "objectid": 636735,
        "globalid": "{DEFD5E83-8594-4580-9D8E-4167EF8ED9DE}",
        "what_was_observed": "Crocodile",
        "sighting": "I did",
        "sighttime": 1721858220000,
        "species": "Freshwater",
        "sightingid": "250724TSV1",
        "publicstatus": "Under Investigation",
        "publicinfo": "",
        "managementunit": "Townsville Operations",
        "lga": "Townsville City",
        "created_date": 1721858498000,
        "last_edited_date": 1721860053000,
        "closeddate": null
      }
    }
  ]
}
