{
  "type": "FeatureCollection",
  "features": [
    {
      "type": "Feature",
      "id": 1051142,
      "geometry": {
        "type": "Point",
        "coordinates": [
          151.36109999991231,
          -23.955130000334229
        ]
      },
      "properties": {
        "objectid": 1051142,
        "globalid": "{EB863ED7-8BF8-4AF9-B63C-5BFF8BC9ABDC}",
        "what_was_observed": "Crocodile",
        "sighting": "I did",
        "sighttime": 1750762800000,
        "species": "Estuarine",
        "sightingid": "240625GLT1",
        "publicstatus": "Under Investigation",
        "publicinfo": "",
        "managementunit": "Capricornia Operations",
        "lga": "Gladstone Regional",
        "created_date": 1750757923000,
        "last_edited_date": 1750761374000,
        "closeddate": null
      }
    }
  ]
}
