{
  "type": "FeatureCollection",
  "features": [
    {
      "type": "Feature",
      "id": 1407546,
      "geometry": {
        "type": "Point",
        "coordinates": [
          146.08467466402232,
          -17.800559717335492
        ]
      },
      "properties": {
        "objectid": 1407546,
        "globalid": "{11C381E4-6682-4D46-9A01-AEFFF06038DB}",
        "what_was_observed": "Crocodile",
        "sighting": "I did",
        "sighttime": 1780886640000,
        "species": "Estuarine",
        "sightingid": "080626CWC1",
        "publicstatus": "Under Investigation",
        "publicinfo": "",
        "managementunit": "Innisfail Operations",
        "lga": "Cassowary Coast Regional",
        "created_date": 1780886785000,
        "last_edited_date": 1780889271000,
        "closeddate": null
      }
    },
    {
      "type": "Feature",
      "id": 1408345,
      "geometry": {
        "type": "Point",
        "coordinates": [
          148.52406305472456,
          -20.405406268020577
        ]
      },
      "properties": {
        "objectid": 1408345,
        "globalid": "{4CD799E2-D957-409E-BCFE-EADF9771EF35}",
        "what_was_observed": "Crocodile",
        "sighting": "I did",
        "sighttime": 1780885200000,
        "species": "Estuarine",
        "sightingid": "080626WTS1",
        "publicstatus": "Under Investigation",
        "publicinfo": "",
        "managementunit": "Mackay Operations",
        "lga": "Whitsunday Regional",
        "created_date": 1780890295000,
        "last_edited_date": 1780899520000,
        "closeddate": null
      }
    },
    {
      "type": "Feature",
      "id": 1407945,
      "geometry": {
        "type": "Point",
        "coordinates": [
          150.48633999960975,
          -23.327459999947298
        ]
      },
      "properties": {
        "objectid": 1407945,
        "globalid": "{AEB6C833-A2C3-4F44-AD1D-8CC160E58A88}",
        "what_was_observed": "Crocodile",
        "sighting": "Somebody else",
        "sighttime": 1780882200000,
        "species": "Estuarine",
        "sightingid": "080626ROC1",
        "publicstatus": "Under Investigation",
        "publicinfo": "",
        "managementunit": "Capricornia Operations",
        "lga": "Rockhampton Regional",
        "created_date": 1780883567000,
        "last_edited_date": 1780894886000,
        "closeddate": null
      }
    }
  ]
}
