{
  "type": "FeatureCollection",
  "features": [
    {
      "type": "Feature",
      "id": 716737,
      "geometry": {
        "type": "Point",
        "coordinates": [
          145.4710200001966,
          -16.538590000112716
        ]
      },
      "properties": {
        "objectid": 716737,
        "globalid": "{D578E334-FBF0-4718-80AE-E97EC8130395}",
        "what_was_observed": "Crocodile",
        "sighting": "I did",
        "sighttime": 1728523800000,
        "species": "Estuarine",
        "sightingid": "101024DUG1",
        "publicstatus": "Under Investigation",
        "publicinfo": "",
        "managementunit": "Cairns Operations",
        "lga": "Douglas Shire",
        "created_date": 1728525311000,
        "last_edited_date": 1728526115000,
        "closeddate": null
      }
    },
    {
      "type": "Feature",
      "id": 716338,
      "geometry": {
        "type": "Point",
        "coordinates": [
          144.2037800003122,
          -20.848110000241412
        ]
      },
      "properties": {
        "objectid": 716338,
        "globalid": "{DD2627D4-3752-47AA-92F3-E39F7FC82A79}",
        "what_was_observed": "Crocodile",
        "sighting": "I did",
        "sighttime": 1728521820000,
        "species": "Freshwater",
        "sightingid": "101024FLD2",
        "publicstatus": "Under Investigation",
        "publicinfo": "",
        "managementunit": "Remote Operations",
        "lga": "Flinders Shire",
        "created_date": 1728522224000,
        "last_edited_date": 1728522631000,
        "closeddate": null
      }
    },
    {
      "type": "Feature",
      "id": 716337,
      "geometry": {
        "type": "Point",
        "coordinates": [
          144.20402999965916,
          -20.850329999746748
        ]
      },
      "properties": {
        "objectid": 716337,
        "globalid": "{44193934-633C-4698-BB07-B1AEC00FD1E8}",
        "what_was_observed": "Crocodile",
        "sighting": "I did",
        "sighttime": 1728521640000,
        "species": "Freshwater",
        "sightingid": "101024FLD1",
        "publicstatus": "Under Investigation",
        "publicinfo": "",
        "managementunit": "Remote Operations",
        "lga": "Flinders Shire",
        "created_date": 1728521799000,
        "last_edited_date": 1728522560000,
        "closeddate": null
      }
    }
  ]
}
